bandaid/__init__.py
bandaid/__main__.py
bandaid/agent.py
bandaid-1.1.2.dist-info/METADATA
bandaid-1.1.2.dist-info/WHEEL
bandaid-1.1.2.dist-info/entry_points.txt
bandaid-1.1.2.dist-info/top_level.txt
bandaid-1.1.2.dist-info/RECORD
