Metadata-Version: 2.1
Name: bandaid
Version: 1.1.2
Summary: Get band tour info and watchlist from the command line
Home-page: https://github.com/jamesacampbell/bandaid
Author: James Campbell
Author-email: james@jamescampbell.us
License: GPLv3
Download-URL: https://github.com/jamesacampbell/bandaid/archive/1.1.2.tar.gz
Keywords: band,tracking,tour-dates,music-tracking,bands
Platform: UNKNOWN
Classifier: Programming Language :: Python :: 3 :: Only
Requires-Dist: pprint
Requires-Dist: bs4
Requires-Dist: requests
